vincent_qt
