Metadata-Version: 1.1
Name: vincent-qt
Version: 0.0.3
Summary: Vincent in QtWidgets applications
Home-page: https://bitbucket.org/rominf/vincent-qt
Author: Roman Inflianskas
Author-email: infroma@gmail.com
License: LGPLv3+
Keywords: vincent plot chart qt
Platform: UNKNOWN
Classifier: Development Status :: 3 - Alpha
Classifier: Intended Audience :: Developers
Classifier: Topic :: Scientific/Engineering :: Visualization
Classifier: License :: OSI Approved :: GNU Lesser General Public License v3 or later (LGPLv3+)
Classifier: Programming Language :: Python :: 3
Classifier: Programming Language :: Python :: 3.1
Classifier: Programming Language :: Python :: 3.2
Classifier: Programming Language :: Python :: 3.3
Classifier: Programming Language :: Python :: 3.4
